jupyterhub_sphinx_theme/__init__.py
jupyterhub_sphinx_theme/assets/scripts/.gitkeep
jupyterhub_sphinx_theme/assets/styles/abstract/_variables.scss
jupyterhub_sphinx_theme/assets/styles/content/typography.scss
jupyterhub_sphinx_theme/assets/styles/jupyterhub-sphinx-theme.scss
jupyterhub_sphinx_theme/assets/styles/sections/_header.scss
jupyterhub_sphinx_theme/theme/jupyterhub-sphinx-theme/footer.html
jupyterhub_sphinx_theme/theme/jupyterhub-sphinx-theme/static/favicon.ico
jupyterhub_sphinx_theme/theme/jupyterhub-sphinx-theme/static/hub-rectangle-dark.svg
jupyterhub_sphinx_theme/theme/jupyterhub-sphinx-theme/static/hub-rectangle.svg
jupyterhub_sphinx_theme/theme/jupyterhub-sphinx-theme/static/styles/jupyterhub-sphinx-theme.css
jupyterhub_sphinx_theme/theme/jupyterhub-sphinx-theme/static/styles/jupyterhub-sphinx-theme.css.map
jupyterhub_sphinx_theme/theme/jupyterhub-sphinx-theme/theme.conf
jupyterhub_sphinx_theme-0.1.0.dist-info/LICENSE
jupyterhub_sphinx_theme-0.1.0.dist-info/METADATA
jupyterhub_sphinx_theme-0.1.0.dist-info/WHEEL
jupyterhub_sphinx_theme-0.1.0.dist-info/entry_points.txt
jupyterhub_sphinx_theme-0.1.0.dist-info/RECORD