Metadata-Version: 2.1
Name: jupyterhub-sphinx-theme
Version: 0.1.0
Summary: JupyterHub's Documentation Theme.
Author-Email: JupyterHub <hello@jupyter.org>
License: BSD 3-Clause License
Classifier: Framework :: Sphinx
Classifier: Framework :: Sphinx :: Theme
Classifier: License :: OSI Approved :: MIT License
Classifier: Environment :: Web Environment
Classifier: Intended Audience :: Developers
Classifier: Programming Language :: Python :: 3
Classifier: Operating System :: OS Independent
Classifier: Topic :: Documentation
Classifier: Topic :: Software Development :: Documentation
Project-URL: Organization, https://jupyter.org
Requires-Python: >=3.8
Requires-Dist: myst-parser
Requires-Dist: pydata-sphinx-theme>=0.14.0
Requires-Dist: sphinx-copybutton
Requires-Dist: sphinxext-opengraph
Requires-Dist: sphinx-theme-builder[cli]; extra == "dev"
Provides-Extra: dev
